[{"arguments":["clang","-Wno-documentation-unknown-command","-Wno-unknown-warning-option","-Wno-unknown-pragmas","-nostdinc","-nostdinc++","-Wall","-g","-Wall","-Wextra","-Wextra","-fexceptions","-mthreads","-fsyntax-only","-m64","--target=x86_64-w64-mingw32","-std=gnu++17","-DUNICODE","-D_UNICODE","-DWIN32","-DMINGW_HAS_SECURE_API","-DQT_QML_DEBUG","-DQT_NO_DEBUG","-DQT_OPENGLWIDGETS_LIB","-DQT_OPENGL_LIB","-DQT_WIDGETS_LIB","-DQT_GUI_LIB","-DQT_CORE_LIB","-DQT_NEEDS_QMAIN","-DQ_CREATOR_RUN","-DQT_ANNOTATE_FUNCTION(x)=__attribute__((annotate(#x)))","-IC:\\Qt\\Tools\\QtCreator\\share\\qtcreator\\cplusplus\\wrappedMingwHeaders","-IC:\\Qt\\Tools\\QtCreator\\share\\qtcreator\\cplusplus\\wrappedQtHeaders","-IC:\\Qt\\Tools\\QtCreator\\share\\qtcreator\\cplusplus\\wrappedQtHeaders\\QtCore","-IG:\\MIRI\\Q2\\FRR\\ViewerPBS25-students","-IC:\\Qt\\Tools\\vcpkg-master\\vcpkg-master\\installed\\x64-windows\\include","-IC:\\Qt\\6.8.2\\mingw_64\\include","-IC:\\Qt\\6.8.2\\mingw_64\\include\\QtOpenGLWidgets","-IC:\\Qt\\6.8.2\\mingw_64\\include\\QtOpenGL","-IC:\\Qt\\6.8.2\\mingw_64\\include\\QtWidgets","-IC:\\Qt\\6.8.2\\mingw_64\\include\\QtGui","-IC:\\Qt\\6.8.2\\mingw_64\\include\\QtCore","-IG:\\MIRI\\Q2\\FRR\\ViewerPBS25-students\\release","-IC:\\Qt\\6.8.2\\mingw_64\\mkspecs\\win32-g++","-isystem","C:\\Qt\\Tools\\mingw1310_64\\lib\\gcc\\x86_64-w64-mingw32\\13.1.0\\include\\c++","-isystem","C:\\Qt\\Tools\\mingw1310_64\\lib\\gcc\\x86_64-w64-mingw32\\13.1.0\\include\\c++\\x86_64-w64-mingw32","-isystem","C:\\Qt\\Tools\\mingw1310_64\\lib\\gcc\\x86_64-w64-mingw32\\13.1.0\\include\\c++\\backward","-isystem","C:\\Qt\\Tools\\QtCreator\\bin\\clang\\lib\\clang\\19\\include","-isystem","C:\\Qt\\Tools\\mingw1310_64\\x86_64-w64-mingw32\\include","-fmessage-length=0","-fdiagnostics-show-note-include-stack","-fretain-comments-from-system-headers","-fmacro-backtrace-limit=0","-ferror-limit=1000","-x","c++","G:\\MIRI\\Q2\\FRR\\ViewerPBS25-students\\triangle_mesh.cc"],"directory":"G:/MIRI/Q2/FRR/ViewerPBS25-students/build/Desktop_Qt_6_8_2_MinGW_64_bit-Profile/.qtc_clangd","file":"G:/MIRI/Q2/FRR/ViewerPBS25-students/triangle_mesh.cc"},{"arguments":["clang","-Wno-documentation-unknown-command","-Wno-unknown-warning-option","-Wno-unknown-pragmas","-nostdinc","-nostdinc++","-Wall","-g","-Wall","-Wextra","-Wextra","-fexceptions","-mthreads","-fsyntax-only","-m64","--target=x86_64-w64-mingw32","-std=gnu++17","-DUNICODE","-D_UNICODE","-DWIN32","-DMINGW_HAS_SECURE_API","-DQT_QML_DEBUG","-DQT_NO_DEBUG","-DQT_OPENGLWIDGETS_LIB","-DQT_OPENGL_LIB","-DQT_WIDGETS_LIB","-DQT_GUI_LIB","-DQT_CORE_LIB","-DQT_NEEDS_QMAIN","-DQ_CREATOR_RUN","-DQT_ANNOTATE_FUNCTION(x)=__attribute__((annotate(#x)))","-IC:\\Qt\\Tools\\QtCreator\\share\\qtcreator\\cplusplus\\wrappedMingwHeaders","-IC:\\Qt\\Tools\\QtCreator\\share\\qtcreator\\cplusplus\\wrappedQtHeaders","-IC:\\Qt\\Tools\\QtCreator\\share\\qtcreator\\cplusplus\\wrappedQtHeaders\\QtCore","-IG:\\MIRI\\Q2\\FRR\\ViewerPBS25-students","-IC:\\Qt\\Tools\\vcpkg-master\\vcpkg-master\\installed\\x64-windows\\include","-IC:\\Qt\\6.8.2\\mingw_64\\include","-IC:\\Qt\\6.8.2\\mingw_64\\include\\QtOpenGLWidgets","-IC:\\Qt\\6.8.2\\mingw_64\\include\\QtOpenGL","-IC:\\Qt\\6.8.2\\mingw_64\\include\\QtWidgets","-IC:\\Qt\\6.8.2\\mingw_64\\include\\QtGui","-IC:\\Qt\\6.8.2\\mingw_64\\include\\QtCore","-IG:\\MIRI\\Q2\\FRR\\ViewerPBS25-students\\release","-IC:\\Qt\\6.8.2\\mingw_64\\mkspecs\\win32-g++","-isystem","C:\\Qt\\Tools\\mingw1310_64\\lib\\gcc\\x86_64-w64-mingw32\\13.1.0\\include\\c++","-isystem","C:\\Qt\\Tools\\mingw1310_64\\lib\\gcc\\x86_64-w64-mingw32\\13.1.0\\include\\c++\\x86_64-w64-mingw32","-isystem","C:\\Qt\\Tools\\mingw1310_64\\lib\\gcc\\x86_64-w64-mingw32\\13.1.0\\include\\c++\\backward","-isystem","C:\\Qt\\Tools\\QtCreator\\bin\\clang\\lib\\clang\\19\\include","-isystem","C:\\Qt\\Tools\\mingw1310_64\\x86_64-w64-mingw32\\include","-fmessage-length=0","-fdiagnostics-show-note-include-stack","-fretain-comments-from-system-headers","-fmacro-backtrace-limit=0","-ferror-limit=1000","-x","c++","G:\\MIRI\\Q2\\FRR\\ViewerPBS25-students\\mesh_io.cc"],"directory":"G:/MIRI/Q2/FRR/ViewerPBS25-students/build/Desktop_Qt_6_8_2_MinGW_64_bit-Profile/.qtc_clangd","file":"G:/MIRI/Q2/FRR/ViewerPBS25-students/mesh_io.cc"},{"arguments":["clang","-Wno-documentation-unknown-command","-Wno-unknown-warning-option","-Wno-unknown-pragmas","-nostdinc","-nostdinc++","-Wall","-g","-Wall","-Wextra","-Wextra","-fexceptions","-mthreads","-fsyntax-only","-m64","--target=x86_64-w64-mingw32","-std=gnu++17","-DUNICODE","-D_UNICODE","-DWIN32","-DMINGW_HAS_SECURE_API","-DQT_QML_DEBUG","-DQT_NO_DEBUG","-DQT_OPENGLWIDGETS_LIB","-DQT_OPENGL_LIB","-DQT_WIDGETS_LIB","-DQT_GUI_LIB","-DQT_CORE_LIB","-DQT_NEEDS_QMAIN","-DQ_CREATOR_RUN","-DQT_ANNOTATE_FUNCTION(x)=__attribute__((annotate(#x)))","-IC:\\Qt\\Tools\\QtCreator\\share\\qtcreator\\cplusplus\\wrappedMingwHeaders","-IC:\\Qt\\Tools\\QtCreator\\share\\qtcreator\\cplusplus\\wrappedQtHeaders","-IC:\\Qt\\Tools\\QtCreator\\share\\qtcreator\\cplusplus\\wrappedQtHeaders\\QtCore","-IG:\\MIRI\\Q2\\FRR\\ViewerPBS25-students","-IC:\\Qt\\Tools\\vcpkg-master\\vcpkg-master\\installed\\x64-windows\\include","-IC:\\Qt\\6.8.2\\mingw_64\\include","-IC:\\Qt\\6.8.2\\mingw_64\\include\\QtOpenGLWidgets","-IC:\\Qt\\6.8.2\\mingw_64\\include\\QtOpenGL","-IC:\\Qt\\6.8.2\\mingw_64\\include\\QtWidgets","-IC:\\Qt\\6.8.2\\mingw_64\\include\\QtGui","-IC:\\Qt\\6.8.2\\mingw_64\\include\\QtCore","-IG:\\MIRI\\Q2\\FRR\\ViewerPBS25-students\\release","-IC:\\Qt\\6.8.2\\mingw_64\\mkspecs\\win32-g++","-isystem","C:\\Qt\\Tools\\mingw1310_64\\lib\\gcc\\x86_64-w64-mingw32\\13.1.0\\include\\c++","-isystem","C:\\Qt\\Tools\\mingw1310_64\\lib\\gcc\\x86_64-w64-mingw32\\13.1.0\\include\\c++\\x86_64-w64-mingw32","-isystem","C:\\Qt\\Tools\\mingw1310_64\\lib\\gcc\\x86_64-w64-mingw32\\13.1.0\\include\\c++\\backward","-isystem","C:\\Qt\\Tools\\QtCreator\\bin\\clang\\lib\\clang\\19\\include","-isystem","C:\\Qt\\Tools\\mingw1310_64\\x86_64-w64-mingw32\\include","-fmessage-length=0","-fdiagnostics-show-note-include-stack","-fretain-comments-from-system-headers","-fmacro-backtrace-limit=0","-ferror-limit=1000","-x","c++","G:\\MIRI\\Q2\\FRR\\ViewerPBS25-students\\main.cc"],"directory":"G:/MIRI/Q2/FRR/ViewerPBS25-students/build/Desktop_Qt_6_8_2_MinGW_64_bit-Profile/.qtc_clangd","file":"G:/MIRI/Q2/FRR/ViewerPBS25-students/main.cc"},{"arguments":["clang","-Wno-documentation-unknown-command","-Wno-unknown-warning-option","-Wno-unknown-pragmas","-nostdinc","-nostdinc++","-Wall","-g","-Wall","-Wextra","-Wextra","-fexceptions","-mthreads","-fsyntax-only","-m64","--target=x86_64-w64-mingw32","-std=gnu++17","-DUNICODE","-D_UNICODE","-DWIN32","-DMINGW_HAS_SECURE_API","-DQT_QML_DEBUG","-DQT_NO_DEBUG","-DQT_OPENGLWIDGETS_LIB","-DQT_OPENGL_LIB","-DQT_WIDGETS_LIB","-DQT_GUI_LIB","-DQT_CORE_LIB","-DQT_NEEDS_QMAIN","-DQ_CREATOR_RUN","-DQT_ANNOTATE_FUNCTION(x)=__attribute__((annotate(#x)))","-IC:\\Qt\\Tools\\QtCreator\\share\\qtcreator\\cplusplus\\wrappedMingwHeaders","-IC:\\Qt\\Tools\\QtCreator\\share\\qtcreator\\cplusplus\\wrappedQtHeaders","-IC:\\Qt\\Tools\\QtCreator\\share\\qtcreator\\cplusplus\\wrappedQtHeaders\\QtCore","-IG:\\MIRI\\Q2\\FRR\\ViewerPBS25-students","-IC:\\Qt\\Tools\\vcpkg-master\\vcpkg-master\\installed\\x64-windows\\include","-IC:\\Qt\\6.8.2\\mingw_64\\include","-IC:\\Qt\\6.8.2\\mingw_64\\include\\QtOpenGLWidgets","-IC:\\Qt\\6.8.2\\mingw_64\\include\\QtOpenGL","-IC:\\Qt\\6.8.2\\mingw_64\\include\\QtWidgets","-IC:\\Qt\\6.8.2\\mingw_64\\include\\QtGui","-IC:\\Qt\\6.8.2\\mingw_64\\include\\QtCore","-IG:\\MIRI\\Q2\\FRR\\ViewerPBS25-students\\release","-IC:\\Qt\\6.8.2\\mingw_64\\mkspecs\\win32-g++","-isystem","C:\\Qt\\Tools\\mingw1310_64\\lib\\gcc\\x86_64-w64-mingw32\\13.1.0\\include\\c++","-isystem","C:\\Qt\\Tools\\mingw1310_64\\lib\\gcc\\x86_64-w64-mingw32\\13.1.0\\include\\c++\\x86_64-w64-mingw32","-isystem","C:\\Qt\\Tools\\mingw1310_64\\lib\\gcc\\x86_64-w64-mingw32\\13.1.0\\include\\c++\\backward","-isystem","C:\\Qt\\Tools\\QtCreator\\bin\\clang\\lib\\clang\\19\\include","-isystem","C:\\Qt\\Tools\\mingw1310_64\\x86_64-w64-mingw32\\include","-fmessage-length=0","-fdiagnostics-show-note-include-stack","-fretain-comments-from-system-headers","-fmacro-backtrace-limit=0","-ferror-limit=1000","-x","c++","G:\\MIRI\\Q2\\FRR\\ViewerPBS25-students\\main_window.cc"],"directory":"G:/MIRI/Q2/FRR/ViewerPBS25-students/build/Desktop_Qt_6_8_2_MinGW_64_bit-Profile/.qtc_clangd","file":"G:/MIRI/Q2/FRR/ViewerPBS25-students/main_window.cc"},{"arguments":["clang","-Wno-documentation-unknown-command","-Wno-unknown-warning-option","-Wno-unknown-pragmas","-nostdinc","-nostdinc++","-Wall","-g","-Wall","-Wextra","-Wextra","-fexceptions","-mthreads","-fsyntax-only","-m64","--target=x86_64-w64-mingw32","-std=gnu++17","-DUNICODE","-D_UNICODE","-DWIN32","-DMINGW_HAS_SECURE_API","-DQT_QML_DEBUG","-DQT_NO_DEBUG","-DQT_OPENGLWIDGETS_LIB","-DQT_OPENGL_LIB","-DQT_WIDGETS_LIB","-DQT_GUI_LIB","-DQT_CORE_LIB","-DQT_NEEDS_QMAIN","-DQ_CREATOR_RUN","-DQT_ANNOTATE_FUNCTION(x)=__attribute__((annotate(#x)))","-IC:\\Qt\\Tools\\QtCreator\\share\\qtcreator\\cplusplus\\wrappedMingwHeaders","-IC:\\Qt\\Tools\\QtCreator\\share\\qtcreator\\cplusplus\\wrappedQtHeaders","-IC:\\Qt\\Tools\\QtCreator\\share\\qtcreator\\cplusplus\\wrappedQtHeaders\\QtCore","-IG:\\MIRI\\Q2\\FRR\\ViewerPBS25-students","-IC:\\Qt\\Tools\\vcpkg-master\\vcpkg-master\\installed\\x64-windows\\include","-IC:\\Qt\\6.8.2\\mingw_64\\include","-IC:\\Qt\\6.8.2\\mingw_64\\include\\QtOpenGLWidgets","-IC:\\Qt\\6.8.2\\mingw_64\\include\\QtOpenGL","-IC:\\Qt\\6.8.2\\mingw_64\\include\\QtWidgets","-IC:\\Qt\\6.8.2\\mingw_64\\include\\QtGui","-IC:\\Qt\\6.8.2\\mingw_64\\include\\QtCore","-IG:\\MIRI\\Q2\\FRR\\ViewerPBS25-students\\release","-IC:\\Qt\\6.8.2\\mingw_64\\mkspecs\\win32-g++","-isystem","C:\\Qt\\Tools\\mingw1310_64\\lib\\gcc\\x86_64-w64-mingw32\\13.1.0\\include\\c++","-isystem","C:\\Qt\\Tools\\mingw1310_64\\lib\\gcc\\x86_64-w64-mingw32\\13.1.0\\include\\c++\\x86_64-w64-mingw32","-isystem","C:\\Qt\\Tools\\mingw1310_64\\lib\\gcc\\x86_64-w64-mingw32\\13.1.0\\include\\c++\\backward","-isystem","C:\\Qt\\Tools\\QtCreator\\bin\\clang\\lib\\clang\\19\\include","-isystem","C:\\Qt\\Tools\\mingw1310_64\\x86_64-w64-mingw32\\include","-fmessage-length=0","-fdiagnostics-show-note-include-stack","-fretain-comments-from-system-headers","-fmacro-backtrace-limit=0","-ferror-limit=1000","-x","c++","G:\\MIRI\\Q2\\FRR\\ViewerPBS25-students\\glwidget.cc"],"directory":"G:/MIRI/Q2/FRR/ViewerPBS25-students/build/Desktop_Qt_6_8_2_MinGW_64_bit-Profile/.qtc_clangd","file":"G:/MIRI/Q2/FRR/ViewerPBS25-students/glwidget.cc"},{"arguments":["clang","-Wno-documentation-unknown-command","-Wno-unknown-warning-option","-Wno-unknown-pragmas","-nostdinc","-nostdinc++","-Wall","-g","-Wall","-Wextra","-Wextra","-fexceptions","-mthreads","-fsyntax-only","-m64","--target=x86_64-w64-mingw32","-std=gnu++17","-DUNICODE","-D_UNICODE","-DWIN32","-DMINGW_HAS_SECURE_API","-DQT_QML_DEBUG","-DQT_NO_DEBUG","-DQT_OPENGLWIDGETS_LIB","-DQT_OPENGL_LIB","-DQT_WIDGETS_LIB","-DQT_GUI_LIB","-DQT_CORE_LIB","-DQT_NEEDS_QMAIN","-DQ_CREATOR_RUN","-DQT_ANNOTATE_FUNCTION(x)=__attribute__((annotate(#x)))","-IC:\\Qt\\Tools\\QtCreator\\share\\qtcreator\\cplusplus\\wrappedMingwHeaders","-IC:\\Qt\\Tools\\QtCreator\\share\\qtcreator\\cplusplus\\wrappedQtHeaders","-IC:\\Qt\\Tools\\QtCreator\\share\\qtcreator\\cplusplus\\wrappedQtHeaders\\QtCore","-IG:\\MIRI\\Q2\\FRR\\ViewerPBS25-students","-IC:\\Qt\\Tools\\vcpkg-master\\vcpkg-master\\installed\\x64-windows\\include","-IC:\\Qt\\6.8.2\\mingw_64\\include","-IC:\\Qt\\6.8.2\\mingw_64\\include\\QtOpenGLWidgets","-IC:\\Qt\\6.8.2\\mingw_64\\include\\QtOpenGL","-IC:\\Qt\\6.8.2\\mingw_64\\include\\QtWidgets","-IC:\\Qt\\6.8.2\\mingw_64\\include\\QtGui","-IC:\\Qt\\6.8.2\\mingw_64\\include\\QtCore","-IG:\\MIRI\\Q2\\FRR\\ViewerPBS25-students\\release","-IC:\\Qt\\6.8.2\\mingw_64\\mkspecs\\win32-g++","-isystem","C:\\Qt\\Tools\\mingw1310_64\\lib\\gcc\\x86_64-w64-mingw32\\13.1.0\\include\\c++","-isystem","C:\\Qt\\Tools\\mingw1310_64\\lib\\gcc\\x86_64-w64-mingw32\\13.1.0\\include\\c++\\x86_64-w64-mingw32","-isystem","C:\\Qt\\Tools\\mingw1310_64\\lib\\gcc\\x86_64-w64-mingw32\\13.1.0\\include\\c++\\backward","-isystem","C:\\Qt\\Tools\\QtCreator\\bin\\clang\\lib\\clang\\19\\include","-isystem","C:\\Qt\\Tools\\mingw1310_64\\x86_64-w64-mingw32\\include","-fmessage-length=0","-fdiagnostics-show-note-include-stack","-fretain-comments-from-system-headers","-fmacro-backtrace-limit=0","-ferror-limit=1000","-x","c++","G:\\MIRI\\Q2\\FRR\\ViewerPBS25-students\\camera.cc"],"directory":"G:/MIRI/Q2/FRR/ViewerPBS25-students/build/Desktop_Qt_6_8_2_MinGW_64_bit-Profile/.qtc_clangd","file":"G:/MIRI/Q2/FRR/ViewerPBS25-students/camera.cc"},{"arguments":["clang","-Wno-documentation-unknown-command","-Wno-unknown-warning-option","-Wno-unknown-pragmas","-nostdinc","-nostdinc++","-Wall","-g","-Wall","-Wextra","-Wextra","-fexceptions","-mthreads","-fsyntax-only","-m64","--target=x86_64-w64-mingw32","-std=gnu++17","-DUNICODE","-D_UNICODE","-DWIN32","-DMINGW_HAS_SECURE_API","-DQT_QML_DEBUG","-DQT_NO_DEBUG","-DQT_OPENGLWIDGETS_LIB","-DQT_OPENGL_LIB","-DQT_WIDGETS_LIB","-DQT_GUI_LIB","-DQT_CORE_LIB","-DQT_NEEDS_QMAIN","-DQ_CREATOR_RUN","-DQT_ANNOTATE_FUNCTION(x)=__attribute__((annotate(#x)))","-IC:\\Qt\\Tools\\QtCreator\\share\\qtcreator\\cplusplus\\wrappedMingwHeaders","-IC:\\Qt\\Tools\\QtCreator\\share\\qtcreator\\cplusplus\\wrappedQtHeaders","-IC:\\Qt\\Tools\\QtCreator\\share\\qtcreator\\cplusplus\\wrappedQtHeaders\\QtCore","-IG:\\MIRI\\Q2\\FRR\\ViewerPBS25-students","-IC:\\Qt\\Tools\\vcpkg-master\\vcpkg-master\\installed\\x64-windows\\include","-IC:\\Qt\\6.8.2\\mingw_64\\include","-IC:\\Qt\\6.8.2\\mingw_64\\include\\QtOpenGLWidgets","-IC:\\Qt\\6.8.2\\mingw_64\\include\\QtOpenGL","-IC:\\Qt\\6.8.2\\mingw_64\\include\\QtWidgets","-IC:\\Qt\\6.8.2\\mingw_64\\include\\QtGui","-IC:\\Qt\\6.8.2\\mingw_64\\include\\QtCore","-IG:\\MIRI\\Q2\\FRR\\ViewerPBS25-students\\release","-IC:\\Qt\\6.8.2\\mingw_64\\mkspecs\\win32-g++","-isystem","C:\\Qt\\Tools\\mingw1310_64\\lib\\gcc\\x86_64-w64-mingw32\\13.1.0\\include\\c++","-isystem","C:\\Qt\\Tools\\mingw1310_64\\lib\\gcc\\x86_64-w64-mingw32\\13.1.0\\include\\c++\\x86_64-w64-mingw32","-isystem","C:\\Qt\\Tools\\mingw1310_64\\lib\\gcc\\x86_64-w64-mingw32\\13.1.0\\include\\c++\\backward","-isystem","C:\\Qt\\Tools\\QtCreator\\bin\\clang\\lib\\clang\\19\\include","-isystem","C:\\Qt\\Tools\\mingw1310_64\\x86_64-w64-mingw32\\include","-fmessage-length=0","-fdiagnostics-show-note-include-stack","-fretain-comments-from-system-headers","-fmacro-backtrace-limit=0","-ferror-limit=1000","-x","c++","G:\\MIRI\\Q2\\FRR\\ViewerPBS25-students\\tiny_obj_loader.cc"],"directory":"G:/MIRI/Q2/FRR/ViewerPBS25-students/build/Desktop_Qt_6_8_2_MinGW_64_bit-Profile/.qtc_clangd","file":"G:/MIRI/Q2/FRR/ViewerPBS25-students/tiny_obj_loader.cc"},{"arguments":["clang","-Wno-documentation-unknown-command","-Wno-unknown-warning-option","-Wno-unknown-pragmas","-nostdinc","-nostdinc++","-Wall","-g","-Wall","-Wextra","-Wextra","-fexceptions","-mthreads","-fsyntax-only","-m64","--target=x86_64-w64-mingw32","-std=gnu++17","-DUNICODE","-D_UNICODE","-DWIN32","-DMINGW_HAS_SECURE_API","-DQT_QML_DEBUG","-DQT_NO_DEBUG","-DQT_OPENGLWIDGETS_LIB","-DQT_OPENGL_LIB","-DQT_WIDGETS_LIB","-DQT_GUI_LIB","-DQT_CORE_LIB","-DQT_NEEDS_QMAIN","-DQ_CREATOR_RUN","-DQT_ANNOTATE_FUNCTION(x)=__attribute__((annotate(#x)))","-IC:\\Qt\\Tools\\QtCreator\\share\\qtcreator\\cplusplus\\wrappedMingwHeaders","-IC:\\Qt\\Tools\\QtCreator\\share\\qtcreator\\cplusplus\\wrappedQtHeaders","-IC:\\Qt\\Tools\\QtCreator\\share\\qtcreator\\cplusplus\\wrappedQtHeaders\\QtCore","-IG:\\MIRI\\Q2\\FRR\\ViewerPBS25-students","-IC:\\Qt\\Tools\\vcpkg-master\\vcpkg-master\\installed\\x64-windows\\include","-IC:\\Qt\\6.8.2\\mingw_64\\include","-IC:\\Qt\\6.8.2\\mingw_64\\include\\QtOpenGLWidgets","-IC:\\Qt\\6.8.2\\mingw_64\\include\\QtOpenGL","-IC:\\Qt\\6.8.2\\mingw_64\\include\\QtWidgets","-IC:\\Qt\\6.8.2\\mingw_64\\include\\QtGui","-IC:\\Qt\\6.8.2\\mingw_64\\include\\QtCore","-IG:\\MIRI\\Q2\\FRR\\ViewerPBS25-students\\release","-IC:\\Qt\\6.8.2\\mingw_64\\mkspecs\\win32-g++","-isystem","C:\\Qt\\Tools\\mingw1310_64\\lib\\gcc\\x86_64-w64-mingw32\\13.1.0\\include\\c++","-isystem","C:\\Qt\\Tools\\mingw1310_64\\lib\\gcc\\x86_64-w64-mingw32\\13.1.0\\include\\c++\\x86_64-w64-mingw32","-isystem","C:\\Qt\\Tools\\mingw1310_64\\lib\\gcc\\x86_64-w64-mingw32\\13.1.0\\include\\c++\\backward","-isystem","C:\\Qt\\Tools\\QtCreator\\bin\\clang\\lib\\clang\\19\\include","-isystem","C:\\Qt\\Tools\\mingw1310_64\\x86_64-w64-mingw32\\include","-fmessage-length=0","-fdiagnostics-show-note-include-stack","-fretain-comments-from-system-headers","-fmacro-backtrace-limit=0","-ferror-limit=1000","-x","c++-header","G:\\MIRI\\Q2\\FRR\\ViewerPBS25-students\\triangle_mesh.h"],"directory":"G:/MIRI/Q2/FRR/ViewerPBS25-students/build/Desktop_Qt_6_8_2_MinGW_64_bit-Profile/.qtc_clangd","file":"G:/MIRI/Q2/FRR/ViewerPBS25-students/triangle_mesh.h"},{"arguments":["clang","-Wno-documentation-unknown-command","-Wno-unknown-warning-option","-Wno-unknown-pragmas","-nostdinc","-nostdinc++","-Wall","-g","-Wall","-Wextra","-Wextra","-fexceptions","-mthreads","-fsyntax-only","-m64","--target=x86_64-w64-mingw32","-std=gnu++17","-DUNICODE","-D_UNICODE","-DWIN32","-DMINGW_HAS_SECURE_API","-DQT_QML_DEBUG","-DQT_NO_DEBUG","-DQT_OPENGLWIDGETS_LIB","-DQT_OPENGL_LIB","-DQT_WIDGETS_LIB","-DQT_GUI_LIB","-DQT_CORE_LIB","-DQT_NEEDS_QMAIN","-DQ_CREATOR_RUN","-DQT_ANNOTATE_FUNCTION(x)=__attribute__((annotate(#x)))","-IC:\\Qt\\Tools\\QtCreator\\share\\qtcreator\\cplusplus\\wrappedMingwHeaders","-IC:\\Qt\\Tools\\QtCreator\\share\\qtcreator\\cplusplus\\wrappedQtHeaders","-IC:\\Qt\\Tools\\QtCreator\\share\\qtcreator\\cplusplus\\wrappedQtHeaders\\QtCore","-IG:\\MIRI\\Q2\\FRR\\ViewerPBS25-students","-IC:\\Qt\\Tools\\vcpkg-master\\vcpkg-master\\installed\\x64-windows\\include","-IC:\\Qt\\6.8.2\\mingw_64\\include","-IC:\\Qt\\6.8.2\\mingw_64\\include\\QtOpenGLWidgets","-IC:\\Qt\\6.8.2\\mingw_64\\include\\QtOpenGL","-IC:\\Qt\\6.8.2\\mingw_64\\include\\QtWidgets","-IC:\\Qt\\6.8.2\\mingw_64\\include\\QtGui","-IC:\\Qt\\6.8.2\\mingw_64\\include\\QtCore","-IG:\\MIRI\\Q2\\FRR\\ViewerPBS25-students\\release","-IC:\\Qt\\6.8.2\\mingw_64\\mkspecs\\win32-g++","-isystem","C:\\Qt\\Tools\\mingw1310_64\\lib\\gcc\\x86_64-w64-mingw32\\13.1.0\\include\\c++","-isystem","C:\\Qt\\Tools\\mingw1310_64\\lib\\gcc\\x86_64-w64-mingw32\\13.1.0\\include\\c++\\x86_64-w64-mingw32","-isystem","C:\\Qt\\Tools\\mingw1310_64\\lib\\gcc\\x86_64-w64-mingw32\\13.1.0\\include\\c++\\backward","-isystem","C:\\Qt\\Tools\\QtCreator\\bin\\clang\\lib\\clang\\19\\include","-isystem","C:\\Qt\\Tools\\mingw1310_64\\x86_64-w64-mingw32\\include","-fmessage-length=0","-fdiagnostics-show-note-include-stack","-fretain-comments-from-system-headers","-fmacro-backtrace-limit=0","-ferror-limit=1000","-x","c++-header","G:\\MIRI\\Q2\\FRR\\ViewerPBS25-students\\mesh_io.h"],"directory":"G:/MIRI/Q2/FRR/ViewerPBS25-students/build/Desktop_Qt_6_8_2_MinGW_64_bit-Profile/.qtc_clangd","file":"G:/MIRI/Q2/FRR/ViewerPBS25-students/mesh_io.h"},{"arguments":["clang","-Wno-documentation-unknown-command","-Wno-unknown-warning-option","-Wno-unknown-pragmas","-nostdinc","-nostdinc++","-Wall","-g","-Wall","-Wextra","-Wextra","-fexceptions","-mthreads","-fsyntax-only","-m64","--target=x86_64-w64-mingw32","-std=gnu++17","-DUNICODE","-D_UNICODE","-DWIN32","-DMINGW_HAS_SECURE_API","-DQT_QML_DEBUG","-DQT_NO_DEBUG","-DQT_OPENGLWIDGETS_LIB","-DQT_OPENGL_LIB","-DQT_WIDGETS_LIB","-DQT_GUI_LIB","-DQT_CORE_LIB","-DQT_NEEDS_QMAIN","-DQ_CREATOR_RUN","-DQT_ANNOTATE_FUNCTION(x)=__attribute__((annotate(#x)))","-IC:\\Qt\\Tools\\QtCreator\\share\\qtcreator\\cplusplus\\wrappedMingwHeaders","-IC:\\Qt\\Tools\\QtCreator\\share\\qtcreator\\cplusplus\\wrappedQtHeaders","-IC:\\Qt\\Tools\\QtCreator\\share\\qtcreator\\cplusplus\\wrappedQtHeaders\\QtCore","-IG:\\MIRI\\Q2\\FRR\\ViewerPBS25-students","-IC:\\Qt\\Tools\\vcpkg-master\\vcpkg-master\\installed\\x64-windows\\include","-IC:\\Qt\\6.8.2\\mingw_64\\include","-IC:\\Qt\\6.8.2\\mingw_64\\include\\QtOpenGLWidgets","-IC:\\Qt\\6.8.2\\mingw_64\\include\\QtOpenGL","-IC:\\Qt\\6.8.2\\mingw_64\\include\\QtWidgets","-IC:\\Qt\\6.8.2\\mingw_64\\include\\QtGui","-IC:\\Qt\\6.8.2\\mingw_64\\include\\QtCore","-IG:\\MIRI\\Q2\\FRR\\ViewerPBS25-students\\release","-IC:\\Qt\\6.8.2\\mingw_64\\mkspecs\\win32-g++","-isystem","C:\\Qt\\Tools\\mingw1310_64\\lib\\gcc\\x86_64-w64-mingw32\\13.1.0\\include\\c++","-isystem","C:\\Qt\\Tools\\mingw1310_64\\lib\\gcc\\x86_64-w64-mingw32\\13.1.0\\include\\c++\\x86_64-w64-mingw32","-isystem","C:\\Qt\\Tools\\mingw1310_64\\lib\\gcc\\x86_64-w64-mingw32\\13.1.0\\include\\c++\\backward","-isystem","C:\\Qt\\Tools\\QtCreator\\bin\\clang\\lib\\clang\\19\\include","-isystem","C:\\Qt\\Tools\\mingw1310_64\\x86_64-w64-mingw32\\include","-fmessage-length=0","-fdiagnostics-show-note-include-stack","-fretain-comments-from-system-headers","-fmacro-backtrace-limit=0","-ferror-limit=1000","-x","c++-header","G:\\MIRI\\Q2\\FRR\\ViewerPBS25-students\\main_window.h"],"directory":"G:/MIRI/Q2/FRR/ViewerPBS25-students/build/Desktop_Qt_6_8_2_MinGW_64_bit-Profile/.qtc_clangd","file":"G:/MIRI/Q2/FRR/ViewerPBS25-students/main_window.h"},{"arguments":["clang","-Wno-documentation-unknown-command","-Wno-unknown-warning-option","-Wno-unknown-pragmas","-nostdinc","-nostdinc++","-Wall","-g","-Wall","-Wextra","-Wextra","-fexceptions","-mthreads","-fsyntax-only","-m64","--target=x86_64-w64-mingw32","-std=gnu++17","-DUNICODE","-D_UNICODE","-DWIN32","-DMINGW_HAS_SECURE_API","-DQT_QML_DEBUG","-DQT_NO_DEBUG","-DQT_OPENGLWIDGETS_LIB","-DQT_OPENGL_LIB","-DQT_WIDGETS_LIB","-DQT_GUI_LIB","-DQT_CORE_LIB","-DQT_NEEDS_QMAIN","-DQ_CREATOR_RUN","-DQT_ANNOTATE_FUNCTION(x)=__attribute__((annotate(#x)))","-IC:\\Qt\\Tools\\QtCreator\\share\\qtcreator\\cplusplus\\wrappedMingwHeaders","-IC:\\Qt\\Tools\\QtCreator\\share\\qtcreator\\cplusplus\\wrappedQtHeaders","-IC:\\Qt\\Tools\\QtCreator\\share\\qtcreator\\cplusplus\\wrappedQtHeaders\\QtCore","-IG:\\MIRI\\Q2\\FRR\\ViewerPBS25-students","-IC:\\Qt\\Tools\\vcpkg-master\\vcpkg-master\\installed\\x64-windows\\include","-IC:\\Qt\\6.8.2\\mingw_64\\include","-IC:\\Qt\\6.8.2\\mingw_64\\include\\QtOpenGLWidgets","-IC:\\Qt\\6.8.2\\mingw_64\\include\\QtOpenGL","-IC:\\Qt\\6.8.2\\mingw_64\\include\\QtWidgets","-IC:\\Qt\\6.8.2\\mingw_64\\include\\QtGui","-IC:\\Qt\\6.8.2\\mingw_64\\include\\QtCore","-IG:\\MIRI\\Q2\\FRR\\ViewerPBS25-students\\release","-IC:\\Qt\\6.8.2\\mingw_64\\mkspecs\\win32-g++","-isystem","C:\\Qt\\Tools\\mingw1310_64\\lib\\gcc\\x86_64-w64-mingw32\\13.1.0\\include\\c++","-isystem","C:\\Qt\\Tools\\mingw1310_64\\lib\\gcc\\x86_64-w64-mingw32\\13.1.0\\include\\c++\\x86_64-w64-mingw32","-isystem","C:\\Qt\\Tools\\mingw1310_64\\lib\\gcc\\x86_64-w64-mingw32\\13.1.0\\include\\c++\\backward","-isystem","C:\\Qt\\Tools\\QtCreator\\bin\\clang\\lib\\clang\\19\\include","-isystem","C:\\Qt\\Tools\\mingw1310_64\\x86_64-w64-mingw32\\include","-fmessage-length=0","-fdiagnostics-show-note-include-stack","-fretain-comments-from-system-headers","-fmacro-backtrace-limit=0","-ferror-limit=1000","-x","c++-header","G:\\MIRI\\Q2\\FRR\\ViewerPBS25-students\\glwidget.h"],"directory":"G:/MIRI/Q2/FRR/ViewerPBS25-students/build/Desktop_Qt_6_8_2_MinGW_64_bit-Profile/.qtc_clangd","file":"G:/MIRI/Q2/FRR/ViewerPBS25-students/glwidget.h"},{"arguments":["clang","-Wno-documentation-unknown-command","-Wno-unknown-warning-option","-Wno-unknown-pragmas","-nostdinc","-nostdinc++","-Wall","-g","-Wall","-Wextra","-Wextra","-fexceptions","-mthreads","-fsyntax-only","-m64","--target=x86_64-w64-mingw32","-std=gnu++17","-DUNICODE","-D_UNICODE","-DWIN32","-DMINGW_HAS_SECURE_API","-DQT_QML_DEBUG","-DQT_NO_DEBUG","-DQT_OPENGLWIDGETS_LIB","-DQT_OPENGL_LIB","-DQT_WIDGETS_LIB","-DQT_GUI_LIB","-DQT_CORE_LIB","-DQT_NEEDS_QMAIN","-DQ_CREATOR_RUN","-DQT_ANNOTATE_FUNCTION(x)=__attribute__((annotate(#x)))","-IC:\\Qt\\Tools\\QtCreator\\share\\qtcreator\\cplusplus\\wrappedMingwHeaders","-IC:\\Qt\\Tools\\QtCreator\\share\\qtcreator\\cplusplus\\wrappedQtHeaders","-IC:\\Qt\\Tools\\QtCreator\\share\\qtcreator\\cplusplus\\wrappedQtHeaders\\QtCore","-IG:\\MIRI\\Q2\\FRR\\ViewerPBS25-students","-IC:\\Qt\\Tools\\vcpkg-master\\vcpkg-master\\installed\\x64-windows\\include","-IC:\\Qt\\6.8.2\\mingw_64\\include","-IC:\\Qt\\6.8.2\\mingw_64\\include\\QtOpenGLWidgets","-IC:\\Qt\\6.8.2\\mingw_64\\include\\QtOpenGL","-IC:\\Qt\\6.8.2\\mingw_64\\include\\QtWidgets","-IC:\\Qt\\6.8.2\\mingw_64\\include\\QtGui","-IC:\\Qt\\6.8.2\\mingw_64\\include\\QtCore","-IG:\\MIRI\\Q2\\FRR\\ViewerPBS25-students\\release","-IC:\\Qt\\6.8.2\\mingw_64\\mkspecs\\win32-g++","-isystem","C:\\Qt\\Tools\\mingw1310_64\\lib\\gcc\\x86_64-w64-mingw32\\13.1.0\\include\\c++","-isystem","C:\\Qt\\Tools\\mingw1310_64\\lib\\gcc\\x86_64-w64-mingw32\\13.1.0\\include\\c++\\x86_64-w64-mingw32","-isystem","C:\\Qt\\Tools\\mingw1310_64\\lib\\gcc\\x86_64-w64-mingw32\\13.1.0\\include\\c++\\backward","-isystem","C:\\Qt\\Tools\\QtCreator\\bin\\clang\\lib\\clang\\19\\include","-isystem","C:\\Qt\\Tools\\mingw1310_64\\x86_64-w64-mingw32\\include","-fmessage-length=0","-fdiagnostics-show-note-include-stack","-fretain-comments-from-system-headers","-fmacro-backtrace-limit=0","-ferror-limit=1000","-x","c++-header","G:\\MIRI\\Q2\\FRR\\ViewerPBS25-students\\camera.h"],"directory":"G:/MIRI/Q2/FRR/ViewerPBS25-students/build/Desktop_Qt_6_8_2_MinGW_64_bit-Profile/.qtc_clangd","file":"G:/MIRI/Q2/FRR/ViewerPBS25-students/camera.h"},{"arguments":["clang","-Wno-documentation-unknown-command","-Wno-unknown-warning-option","-Wno-unknown-pragmas","-nostdinc","-nostdinc++","-Wall","-g","-Wall","-Wextra","-Wextra","-fexceptions","-mthreads","-fsyntax-only","-m64","--target=x86_64-w64-mingw32","-std=gnu++17","-DUNICODE","-D_UNICODE","-DWIN32","-DMINGW_HAS_SECURE_API","-DQT_QML_DEBUG","-DQT_NO_DEBUG","-DQT_OPENGLWIDGETS_LIB","-DQT_OPENGL_LIB","-DQT_WIDGETS_LIB","-DQT_GUI_LIB","-DQT_CORE_LIB","-DQT_NEEDS_QMAIN","-DQ_CREATOR_RUN","-DQT_ANNOTATE_FUNCTION(x)=__attribute__((annotate(#x)))","-IC:\\Qt\\Tools\\QtCreator\\share\\qtcreator\\cplusplus\\wrappedMingwHeaders","-IC:\\Qt\\Tools\\QtCreator\\share\\qtcreator\\cplusplus\\wrappedQtHeaders","-IC:\\Qt\\Tools\\QtCreator\\share\\qtcreator\\cplusplus\\wrappedQtHeaders\\QtCore","-IG:\\MIRI\\Q2\\FRR\\ViewerPBS25-students","-IC:\\Qt\\Tools\\vcpkg-master\\vcpkg-master\\installed\\x64-windows\\include","-IC:\\Qt\\6.8.2\\mingw_64\\include","-IC:\\Qt\\6.8.2\\mingw_64\\include\\QtOpenGLWidgets","-IC:\\Qt\\6.8.2\\mingw_64\\include\\QtOpenGL","-IC:\\Qt\\6.8.2\\mingw_64\\include\\QtWidgets","-IC:\\Qt\\6.8.2\\mingw_64\\include\\QtGui","-IC:\\Qt\\6.8.2\\mingw_64\\include\\QtCore","-IG:\\MIRI\\Q2\\FRR\\ViewerPBS25-students\\release","-IC:\\Qt\\6.8.2\\mingw_64\\mkspecs\\win32-g++","-isystem","C:\\Qt\\Tools\\mingw1310_64\\lib\\gcc\\x86_64-w64-mingw32\\13.1.0\\include\\c++","-isystem","C:\\Qt\\Tools\\mingw1310_64\\lib\\gcc\\x86_64-w64-mingw32\\13.1.0\\include\\c++\\x86_64-w64-mingw32","-isystem","C:\\Qt\\Tools\\mingw1310_64\\lib\\gcc\\x86_64-w64-mingw32\\13.1.0\\include\\c++\\backward","-isystem","C:\\Qt\\Tools\\QtCreator\\bin\\clang\\lib\\clang\\19\\include","-isystem","C:\\Qt\\Tools\\mingw1310_64\\x86_64-w64-mingw32\\include","-fmessage-length=0","-fdiagnostics-show-note-include-stack","-fretain-comments-from-system-headers","-fmacro-backtrace-limit=0","-ferror-limit=1000","-x","c++-header","G:\\MIRI\\Q2\\FRR\\ViewerPBS25-students\\tiny_obj_loader.h"],"directory":"G:/MIRI/Q2/FRR/ViewerPBS25-students/build/Desktop_Qt_6_8_2_MinGW_64_bit-Profile/.qtc_clangd","file":"G:/MIRI/Q2/FRR/ViewerPBS25-students/tiny_obj_loader.h"},{"arguments":["clang","-Wno-documentation-unknown-command","-Wno-unknown-warning-option","-Wno-unknown-pragmas","-nostdinc","-nostdinc++","-Wall","-g","-Wall","-Wextra","-Wextra","-fexceptions","-mthreads","-fsyntax-only","-m64","--target=x86_64-w64-mingw32","-std=gnu++17","-DUNICODE","-D_UNICODE","-DWIN32","-DMINGW_HAS_SECURE_API","-DQT_QML_DEBUG","-DQT_NO_DEBUG","-DQT_OPENGLWIDGETS_LIB","-DQT_OPENGL_LIB","-DQT_WIDGETS_LIB","-DQT_GUI_LIB","-DQT_CORE_LIB","-DQT_NEEDS_QMAIN","-DQ_CREATOR_RUN","-DQT_ANNOTATE_FUNCTION(x)=__attribute__((annotate(#x)))","-IC:\\Qt\\Tools\\QtCreator\\share\\qtcreator\\cplusplus\\wrappedMingwHeaders","-IC:\\Qt\\Tools\\QtCreator\\share\\qtcreator\\cplusplus\\wrappedQtHeaders","-IC:\\Qt\\Tools\\QtCreator\\share\\qtcreator\\cplusplus\\wrappedQtHeaders\\QtCore","-IG:\\MIRI\\Q2\\FRR\\ViewerPBS25-students","-IC:\\Qt\\Tools\\vcpkg-master\\vcpkg-master\\installed\\x64-windows\\include","-IC:\\Qt\\6.8.2\\mingw_64\\include","-IC:\\Qt\\6.8.2\\mingw_64\\include\\QtOpenGLWidgets","-IC:\\Qt\\6.8.2\\mingw_64\\include\\QtOpenGL","-IC:\\Qt\\6.8.2\\mingw_64\\include\\QtWidgets","-IC:\\Qt\\6.8.2\\mingw_64\\include\\QtGui","-IC:\\Qt\\6.8.2\\mingw_64\\include\\QtCore","-IG:\\MIRI\\Q2\\FRR\\ViewerPBS25-students\\release","-IC:\\Qt\\6.8.2\\mingw_64\\mkspecs\\win32-g++","-isystem","C:\\Qt\\Tools\\mingw1310_64\\lib\\gcc\\x86_64-w64-mingw32\\13.1.0\\include\\c++","-isystem","C:\\Qt\\Tools\\mingw1310_64\\lib\\gcc\\x86_64-w64-mingw32\\13.1.0\\include\\c++\\x86_64-w64-mingw32","-isystem","C:\\Qt\\Tools\\mingw1310_64\\lib\\gcc\\x86_64-w64-mingw32\\13.1.0\\include\\c++\\backward","-isystem","C:\\Qt\\Tools\\QtCreator\\bin\\clang\\lib\\clang\\19\\include","-isystem","C:\\Qt\\Tools\\mingw1310_64\\x86_64-w64-mingw32\\include","-fmessage-length=0","-fdiagnostics-show-note-include-stack","-fretain-comments-from-system-headers","-fmacro-backtrace-limit=0","-ferror-limit=1000","-x","c++-header","G:\\MIRI\\Q2\\FRR\\ViewerPBS25-students\\release\\ui_main_window.h"],"directory":"G:/MIRI/Q2/FRR/ViewerPBS25-students/build/Desktop_Qt_6_8_2_MinGW_64_bit-Profile/.qtc_clangd","file":"G:/MIRI/Q2/FRR/ViewerPBS25-students/release/ui_main_window.h"}]